{
    "behavior": "",
    "checkable": false,
    "class": "p",
    "clickable": true,
    "content-desc": "",
    "enabled": true,
    "focusable": true,
    "focused": false,
    "hash": "odFCw945F+iQBRb/vbuYrg==\n",
    "height": 63,
    "hier_level": 0,
    "human_hash": "p_X1299_Y786_W351_H63",
    "index": -1,
    "internal": {
        "elem_dict": {
            "attributes": {},
            "backend_node_id": 15745,
            "flags": {
                "checkable": false,
                "clickable": true,
                "enabled": true,
                "focusable": true,
                "focused": false,
                "scrollable": false
            },
            "height": 63.0,
            "key": "1299_786_351_63_Chickens are showing up in many suburban backyards. They\u2019re relatively easy to raise and don\u2019t take up a lot of space. Having a source of farm-fresh eggs right outside your door may tempt you to give chicken keeping a try. Before you rush out and buy a coop, it\u2019s important to consider a few details. This guide will teach you the basics of how to raise chickens and which  chicken supplies  you need to keep them healthy and happy. We\u2019ll also answer common questions, such as: \u201cHow much do chickens cost?\u201d and \u201cAt what age do chickens start laying eggs?\u201d",
            "tagName": "p",
            "text": "Chickens are showing up in many suburban backyards. They\u2019re relatively easy to raise and don\u2019t take up a lot of space. Having a source of farm-fresh eggs right outside your door may tempt you to give chicken keeping a try. Before you rush out and buy a coop, it\u2019s important to consider a few details. This guide will teach you the basics of how to raise chickens and which  chicken supplies  you need to keep them healthy and happy. We\u2019ll also answer common questions, such as: \u201cHow much do chickens cost?\u201d and \u201cAt what age do chickens start laying eggs?\u201d",
            "width": 351.0,
            "x": 1299.0,
            "y": 786.0
        },
        "location": {
            "x": 1299.0,
            "y": 786.0
        },
        "size": {
            "height": 63.0,
            "width": 351.0
        },
        "tag_name": "p",
        "text": "Chickens are showing up in many suburban backyards. They\u2019re relatively easy to raise and don\u2019t take up a lot of space. Having a source of farm-fresh eggs right outside your door may tempt you to give chicken keeping a try. Before you rush out and buy a coop, it\u2019s important to consider a few details. This guide will teach you the basics of how to raise chickens and which  chicken supplies  you need to keep them healthy and happy. We\u2019ll also answer common questions, such as: \u201cHow much do chickens cost?\u201d and \u201cAt what age do chickens start laying eggs?\u201d"
    },
    "is_transformed": true,
    "package": "",
    "password": false,
    "resource-id": "",
    "scrollable": false,
    "tag_name": "p",
    "text": "Chickens are showing up in many suburban backyards. They\u2019re relatively easy to raise and don\u2019t take up a lot of space. Having a source of farm-fresh eggs right outside your door may tempt you to give chicken keeping a try. Before you rush out and buy a coop, it\u2019s important to consider a few details. This guide will teach you the basics of how to raise chickens and which  chicken supplies  you need to keep them healthy and happy. We\u2019ll also answer common questions, such as: \u201cHow much do chickens cost?\u201d and \u201cAt what age do chickens start laying eggs?\u201d",
    "transformed": true,
    "width": 351,
    "x": 1299,
    "y": 786
}