{
    "behavior": "",
    "checkable": false,
    "class": "a",
    "clickable": true,
    "content-desc": "",
    "enabled": true,
    "focusable": true,
    "focused": false,
    "hash": "sJ6BmzsDSKmkB+LVzFrpQg==\n",
    "height": 17,
    "hier_level": 0,
    "human_hash": "a_X970_Y615_W96_H17",
    "index": -1,
    "internal": {
        "elem_dict": {
            "attributes": {
                "href": "/b/Plumbing-Plumbing-Tools/N-5yc1vZbqlq"
            },
            "backend_node_id": 8506,
            "flags": {
                "checkable": false,
                "clickable": true,
                "enabled": true,
                "focusable": true,
                "focused": false,
                "scrollable": false
            },
            "height": 17.0,
            "key": "970_615_96_17_Plumbing Tools",
            "tagName": "a",
            "text": "Plumbing Tools",
            "width": 96.0,
            "x": 970.0,
            "y": 615.0
        },
        "location": {
            "x": 970.0,
            "y": 615.0
        },
        "size": {
            "height": 17.0,
            "width": 96.0
        },
        "tag_name": "a",
        "text": "Plumbing Tools"
    },
    "is_transformed": true,
    "package": "",
    "password": false,
    "resource-id": "",
    "scrollable": false,
    "tag_name": "a",
    "text": "Plumbing Tools",
    "transformed": true,
    "width": 96,
    "x": 970,
    "y": 615
}