{
    "behavior": "",
    "checkable": false,
    "class": "p",
    "clickable": true,
    "content-desc": "",
    "enabled": true,
    "focusable": true,
    "focused": false,
    "hash": "Mz/94344nph9ELwpaDYqKQ==\n",
    "height": 17,
    "hier_level": 0,
    "human_hash": "p_X490_Y666_W220_H17",
    "index": -1,
    "internal": {
        "elem_dict": {
            "attributes": {},
            "backend_node_id": 7249,
            "flags": {
                "checkable": false,
                "clickable": true,
                "enabled": true,
                "focusable": true,
                "focused": false,
                "scrollable": false
            },
            "height": 17.0,
            "key": "490_666_220_17_Light Switch Installation",
            "tagName": "p",
            "text": "Light Switch Installation",
            "width": 220.0,
            "x": 490.0,
            "y": 666.0
        },
        "location": {
            "x": 490.0,
            "y": 666.0
        },
        "size": {
            "height": 17.0,
            "width": 220.0
        },
        "tag_name": "p",
        "text": "Light Switch Installation"
    },
    "is_transformed": true,
    "package": "",
    "password": false,
    "resource-id": "",
    "scrollable": false,
    "tag_name": "p",
    "text": "Light Switch Installation",
    "transformed": true,
    "width": 220,
    "x": 490,
    "y": 666
}