{
    "behavior": "",
    "checkable": false,
    "class": "p",
    "clickable": true,
    "content-desc": "",
    "enabled": true,
    "focusable": true,
    "focused": false,
    "hash": "cbFB6K353Ou3HL0rQeJJSQ==\n",
    "height": 17,
    "hier_level": 0,
    "human_hash": "p_X250_Y632_W220_H17",
    "index": -1,
    "internal": {
        "elem_dict": {
            "attributes": {},
            "backend_node_id": 6529,
            "flags": {
                "checkable": false,
                "clickable": true,
                "enabled": true,
                "focusable": true,
                "focused": false,
                "scrollable": false
            },
            "height": 17.0,
            "key": "250_632_220_17_Garbage Disposals",
            "tagName": "p",
            "text": "Garbage Disposals",
            "width": 220.0,
            "x": 250.0,
            "y": 632.0
        },
        "location": {
            "x": 250.0,
            "y": 632.0
        },
        "size": {
            "height": 17.0,
            "width": 220.0
        },
        "tag_name": "p",
        "text": "Garbage Disposals"
    },
    "is_transformed": true,
    "package": "",
    "password": false,
    "resource-id": "",
    "scrollable": false,
    "tag_name": "p",
    "text": "Garbage Disposals",
    "transformed": true,
    "width": 220,
    "x": 250,
    "y": 632
}