{
    "behavior": "",
    "checkable": false,
    "class": "div",
    "clickable": true,
    "content-desc": "",
    "enabled": true,
    "focusable": true,
    "focused": false,
    "hash": "b164kQzHA6TIMzFchkc5Vg==\n",
    "height": 17,
    "hier_level": 0,
    "human_hash": "div_X339_Y69_W80_H17",
    "index": -1,
    "internal": {
        "elem_dict": {
            "attributes": {
                "class": "MyAccount__label SimpleFlyout__link--bold"
            },
            "backend_node_id": 21405,
            "flags": {
                "checkable": false,
                "clickable": true,
                "enabled": true,
                "focusable": true,
                "focused": false,
                "scrollable": false
            },
            "height": 17.0,
            "key": "339_69_80_17_My Account",
            "tagName": "div",
            "text": "My Account",
            "width": 80.0,
            "x": 339.0,
            "y": 69.0
        },
        "location": {
            "x": 339.0,
            "y": 69.0
        },
        "size": {
            "height": 17.0,
            "width": 80.0
        },
        "tag_name": "div",
        "text": "My Account"
    },
    "is_transformed": true,
    "package": "",
    "password": false,
    "resource-id": "",
    "scrollable": false,
    "tag_name": "div",
    "text": "My Account",
    "transformed": true,
    "width": 80,
    "x": 339,
    "y": 69
}