{
    "behavior": "",
    "checkable": false,
    "class": "p",
    "clickable": true,
    "content-desc": "",
    "enabled": true,
    "focusable": true,
    "focused": false,
    "hash": "D1gP5PjpjH7VxnUxlAUWQg==\n",
    "height": 17,
    "hier_level": 0,
    "human_hash": "p_X730_Y734_W220_H17",
    "index": -1,
    "internal": {
        "elem_dict": {
            "attributes": {},
            "backend_node_id": 7879,
            "flags": {
                "checkable": false,
                "clickable": true,
                "enabled": true,
                "focusable": true,
                "focused": false,
                "scrollable": false
            },
            "height": 17.0,
            "key": "730_734_220_17_Thermostat Replacement",
            "tagName": "p",
            "text": "Thermostat Replacement",
            "width": 220.0,
            "x": 730.0,
            "y": 734.0
        },
        "location": {
            "x": 730.0,
            "y": 734.0
        },
        "size": {
            "height": 17.0,
            "width": 220.0
        },
        "tag_name": "p",
        "text": "Thermostat Replacement"
    },
    "is_transformed": true,
    "package": "",
    "password": false,
    "resource-id": "",
    "scrollable": false,
    "tag_name": "p",
    "text": "Thermostat Replacement",
    "transformed": true,
    "width": 220,
    "x": 730,
    "y": 734
}