{
    "behavior": "",
    "checkable": false,
    "class": "a",
    "clickable": true,
    "content-desc": "",
    "enabled": true,
    "focusable": true,
    "focused": false,
    "hash": "WiLsdBsJoULTCO6NJ0+PUw==\n",
    "height": 37,
    "hier_level": 0,
    "human_hash": "a_X620_Y863_W340_H37",
    "index": -1,
    "internal": {
        "elem_dict": {
            "attributes": {
                "class": "SimpleFlyout__link",
                "data-cta": "Shop Now",
                "data-image": "//www.homedepot.com/hdus/en_US/DTCCOMNEW/fetch/Global_Assets/shoeflyoutupdated.jpg",
                "data-level": "Storage & Organization",
                "data-link": "//www.homedepot.com/b/Storage-Organization/N-5yc1vZas7e",
                "data-title": "ORGANIZE AND MAXIMIZE YOUR SPACE",
                "href": "//www.homedepot.com/b/Storage-Organization/N-5yc1vZas7e?cm_sp=d-flyout-Storage_and_Organization",
                "title": "Storage & Organization"
            },
            "backend_node_id": 17647,
            "flags": {
                "checkable": false,
                "clickable": true,
                "enabled": true,
                "focusable": true,
                "focused": false,
                "scrollable": false
            },
            "height": 37.0,
            "key": "620_863_340_37_Storage & Organization",
            "tagName": "a",
            "text": "Storage & Organization",
            "width": 340.0,
            "x": 620.0,
            "y": 863.0
        },
        "location": {
            "x": 620.0,
            "y": 863.0
        },
        "size": {
            "height": 37.0,
            "width": 340.0
        },
        "tag_name": "a",
        "text": "Storage & Organization"
    },
    "is_transformed": true,
    "package": "",
    "password": false,
    "resource-id": "",
    "scrollable": false,
    "tag_name": "a",
    "text": "Storage & Organization",
    "transformed": true,
    "width": 340,
    "x": 620,
    "y": 863
}